flexi_mysql/__init__.py
flexi_mysql-0.5.0.dist-info/LICENSE
flexi_mysql-0.5.0.dist-info/METADATA
flexi_mysql-0.5.0.dist-info/WHEEL
flexi_mysql-0.5.0.dist-info/top_level.txt
flexi_mysql-0.5.0.dist-info/RECORD
