Metadata-Version: 2.2
Name: flexi-mysql
Version: 0.5.0
Summary: Python package for simplyfying querying process of mysql
Author: imEternity
License: MIT License
Project-URL: Homepage, https://github.com/eternity2745/flexi-mysql#readme
Project-URL: Repository, https://github.com/eternity2745/flexi-mysql
Keywords: mysql,simple,database,sql
Classifier: Development Status :: 5 - Production/Stable
Classifier: Environment :: Console
Classifier: License :: OSI Approved :: MIT License
Classifier: Programming Language :: Python :: 3
Classifier: Topic :: Utilities
Classifier: Topic :: Database
License-File: LICENSE
Requires-Dist: mysql-connector-python
